electrical/DCCircuits.py
electrical/__init__.py
electrical/info.py
electrical-1.0.0.dist-info/LICENSE
electrical-1.0.0.dist-info/METADATA
electrical-1.0.0.dist-info/WHEEL
electrical-1.0.0.dist-info/top_level.txt
electrical-1.0.0.dist-info/RECORD
