Metadata-Version: 2.1
Name: electrical
Version: 1.0.0
Summary: Electrical Python Library
Home-page: https://github.com/venkataswamyr/python
Author: Venkataswamy R
Author-email: venkataswamy.r@gmail.com
License: UNKNOWN
Platform: UNKNOWN
Classifier: Programming Language :: Python :: 3
Classifier: License :: OSI Approved :: MIT License
Classifier: Operating System :: OS Independent
Requires-Python: >=3.6
